PolyQ/__init__.py
PolyQ/engine.py
PolyQ/simulation.py
polyq-0.1.0.dist-info/licenses/LICENSE
polyq-0.1.0.dist-info/METADATA
polyq-0.1.0.dist-info/WHEEL
polyq-0.1.0.dist-info/top_level.txt
polyq-0.1.0.dist-info/RECORD
