Metadata-Version: 2.4
Name: PolyQ
Version: 0.1.0
Summary: A novel approach to simulate Quantum Circuits using Boolean Polynomials.
Author-email: "C. A. Jothishwaran" <jc_a@ece.iitr.ac.in>, Aarav Ratra <a_ratra@ph.iitr.ac.in>, Satyam Sonaniya <satyam_s@ece.iitr.ac.in>
License: ```
Project-URL: Homepage, https://github.com/QSDAL-IITR/PolyQ
Requires-Python: >=3.11
License-File: LICENSE
Requires-Dist: numpy>=2
Requires-Dist: qiskit>=2.0.0
Dynamic: license-file
